scpyce/__init__.py
scpyce/database/__init__.py
scpyce/database/add_mixin.py
scpyce/database/delete_mixin.py
scpyce/database/get_mixin.py
scpyce/database/model.py
scpyce/database/tables_mixin.py
scpyce/database/update_mixin.py
scpyce/geometry/__init__.py
scpyce/geometry/mesh.py
scpyce/geometry/plane.py
scpyce/geometry/vector3d.py
scpyce/objects/__init__.py
scpyce/objects/element.py
scpyce/objects/load.py
scpyce/objects/properties.py
scpyce/plot/__init__.py
scpyce/plot/plot.py
database3d-0.1.0.dist-info/LICENSE
database3d-0.1.0.dist-info/METADATA
database3d-0.1.0.dist-info/WHEEL
database3d-0.1.0.dist-info/top_level.txt
database3d-0.1.0.dist-info/RECORD
